Metadata-Version: 2.2
Name: e621nete926net1
Version: 62.19.26
Summary: Dont open this
Author: Compocube
Author-email: davletshinsss@mail.ru
Dynamic: author
Dynamic: author-email
Dynamic: summary
